pagerduty_events_api/__init__.py
pagerduty_events_api/pagerduty_incident.py
pagerduty_events_api/pagerduty_rest_client.py
pagerduty_events_api/pagerduty_service.py
pagerduty_events_api-0.3.0.dist-info/DESCRIPTION.rst
pagerduty_events_api-0.3.0.dist-info/METADATA
pagerduty_events_api-0.3.0.dist-info/RECORD
pagerduty_events_api-0.3.0.dist-info/WHEEL
pagerduty_events_api-0.3.0.dist-info/metadata.json
pagerduty_events_api-0.3.0.dist-info/top_level.txt
