Metadata-Version: 2.0
Name: pagerduty-events-api
Version: 0.3.0
Summary: Python wrapper for Pagerduty Events API
Home-page: https://github.com/BlasiusVonSzerencsi/pagerduty-events-api
Author: Balazs Szerencsi
Author-email: balazs.szerencsi@icloud.com
License: MIT
Download-URL: https://github.com/BlasiusVonSzerencsi/pagerduty-events-api/tarball/0.3.0
Keywords: pagerduty,event,api,incident,trigger,acknowledge,resolve
Platform: UNKNOWN
Requires-Dist: requests
